{
  "Animefinder.js": {
    "views": 206,
    "author": "zen"
  },
  "Lyrics-Search.js": {
    "views": 62,
    "author": "zen"
  },
  "Webpilot AI (Web Search).js": {
    "views": 52,
    "author": "zen"
  },
  "iqc.js": {
    "views": 120,
    "author": "zen"
  },
  "youtubedownloader.js": {
    "views": 315,
    "author": "zen"
  },
  "tiktok-downloader.js": {
    "views": 54,
    "author": "zen"
  },
  "imageupscaler.js": {
    "views": 53,
    "author": "Unknown"
  },
  "uploadmeganz.js": {
    "views": 47,
    "author": "zen"
  },
  "imagetopixel.js": {
    "views": 40,
    "author": "zen"
  },
  "meganzdl.js": {
    "views": 26,
    "author": "zen"
  },
  "youtube-summarizer.js": {
    "views": 105,
    "author": "zen"
  },
  "tourl.js": {
    "views": 203,
    "author": "zen"
  },
  "imagedit&toghibli.js": {
    "views": 227,
    "author": "zen"
  },
  "speedtest.js": {
    "views": 204,
    "author": "zen"
  },
  "youtube-transcript.js": {
    "views": 140,
    "author": "zen"
  },
  "apple-music.js": {
    "views": 156,
    "author": "zen"
  },
  "tofigure.js": 2133,
  "tofigure-update.js": {
    "views": 508,
    "author": "zen"
  },
  "test.js": 3,
  "Test.js": {
    "views": 7,
    "author": "Cukii Digital"
  },
  "Speechwriter.js": {
    "views": 74,
    "author": "zen"
  },
  "shorturl.js": {
    "views": 96,
    "author": "zen"
  },
  "Checkphising.js": {
    "views": 146,
    "author": "zen"
  },
  "nsfwcek.js": {
    "views": 112,
    "author": "zen"
  },
  "fesnuk-downloader.js": {
    "views": 109,
    "author": "zen"
  },
  "image2text.js": {
    "views": 106,
    "author": "zen"
  },
  "Faketweet.js": {
    "views": 148,
    "author": "zen"
  },
  "FakeStory-Instagram.js": {
    "views": 808,
    "author": "zen"
  },
  "Threads_Sngkrefbusuk.js": {
    "views": 74,
    "author": "zen"
  },
  "Pinterest_Sengkref.js": {
    "views": 126,
    "author": "zen"
  },
  "RemoveBg-Sngkref.js": {
    "views": 105,
    "author": "zen"
  },
  "Capcutdl-Scrape.js": {
    "views": 106,
    "author": "Unknown"
  },
  "YoutubedownloaderV2.js": {
    "views": 69,
    "author": "zen"
  }
}